{
    "method": "fedavg",
    "epsilon": 5.0,
    "data_distribution": "noniid",
    "config": {
        "dataset": "both",
        "clients": 10,
        "rounds": 20,
        "epsilon": 5.0,
        "delta": 1e-05,
        "local_epochs": 1,
        "batch_size": 128,
        "lr": 0.0007,
        "noniid": true
    },
    "final": {
        "nsl": {
            "acc": 0.750808363871524,
            "f1_macro": 0.1718358843941014,
            "fpr_macro": 0.22838942483365915,
            "latency_ms": 0.0029297079890966415
        },
        "cicids": {
            "acc": 0.7783708333333333,
            "f1_macro": 0.20423917509463255,
            "fpr_macro": 0.13631370603421783,
            "latency_ms": 0.0029297079890966415
        },
        "avg_bytes": 1289256.0
    },
    "per_round": [
        {
            "round": 1,
            "nsl_acc": 0.8835956025005389,
            "cicids_acc": 0.7807375,
            "avg_bytes": 1289256.0,
            "time_s": 98.21666765213013
        },
        {
            "round": 2,
            "nsl_acc": 0.7001778400517353,
            "cicids_acc": 0.6286,
            "avg_bytes": 1289256.0,
            "time_s": 93.96963953971863
        },
        {
            "round": 3,
            "nsl_acc": 0.8688025436516491,
            "cicids_acc": 0.7835541666666667,
            "avg_bytes": 1289256.0,
            "time_s": 90.60684251785278
        },
        {
            "round": 4,
            "nsl_acc": 0.9056100452683769,
            "cicids_acc": 0.6937791666666666,
            "avg_bytes": 1289256.0,
            "time_s": 93.78777265548706
        },
        {
            "round": 5,
            "nsl_acc": 0.6837949989221815,
            "cicids_acc": 0.7761291666666666,
            "avg_bytes": 1289256.0,
            "time_s": 92.81323432922363
        },
        {
            "round": 6,
            "nsl_acc": 0.7365272688079327,
            "cicids_acc": 0.7322208333333333,
            "avg_bytes": 1289256.0,
            "time_s": 89.41467380523682
        },
        {
            "round": 7,
            "nsl_acc": 0.7069411511101531,
            "cicids_acc": 0.5137041666666666,
            "avg_bytes": 1289256.0,
            "time_s": 89.36847710609436
        },
        {
            "round": 8,
            "nsl_acc": 0.5896744988143997,
            "cicids_acc": 0.43857083333333335,
            "avg_bytes": 1289256.0,
            "time_s": 87.73846745491028
        },
        {
            "round": 9,
            "nsl_acc": 0.48154235826686786,
            "cicids_acc": 0.5541208333333333,
            "avg_bytes": 1289256.0,
            "time_s": 97.2196159362793
        },
        {
            "round": 10,
            "nsl_acc": 0.1591129553783143,
            "cicids_acc": 0.476675,
            "avg_bytes": 1289256.0,
            "time_s": 92.5967755317688
        },
        {
            "round": 11,
            "nsl_acc": 0.8132948911403319,
            "cicids_acc": 0.6959958333333334,
            "avg_bytes": 1289256.0,
            "time_s": 92.45333480834961
        },
        {
            "round": 12,
            "nsl_acc": 0.3833530933390817,
            "cicids_acc": 0.5822,
            "avg_bytes": 1289256.0,
            "time_s": 92.78069543838501
        },
        {
            "round": 13,
            "nsl_acc": 0.4263041603793921,
            "cicids_acc": 0.45316666666666666,
            "avg_bytes": 1289256.0,
            "time_s": 91.77907204627991
        },
        {
            "round": 14,
            "nsl_acc": 0.19489652942444494,
            "cicids_acc": 0.19411666666666666,
            "avg_bytes": 1289256.0,
            "time_s": 95.21418762207031
        },
        {
            "round": 15,
            "nsl_acc": 0.33121362362578144,
            "cicids_acc": 0.29618333333333335,
            "avg_bytes": 1289256.0,
            "time_s": 90.92725491523743
        },
        {
            "round": 16,
            "nsl_acc": 0.5663397283897391,
            "cicids_acc": 0.69775,
            "avg_bytes": 1289256.0,
            "time_s": 87.58155941963196
        },
        {
            "round": 17,
            "nsl_acc": 0.921480922612632,
            "cicids_acc": 0.7791958333333333,
            "avg_bytes": 1289256.0,
            "time_s": 87.97150707244873
        },
        {
            "round": 18,
            "nsl_acc": 0.7373625781418409,
            "cicids_acc": 0.7688625,
            "avg_bytes": 1289256.0,
            "time_s": 89.22100305557251
        },
        {
            "round": 19,
            "nsl_acc": 0.6389577495149816,
            "cicids_acc": 0.5109333333333334,
            "avg_bytes": 1289256.0,
            "time_s": 90.91944336891174
        },
        {
            "round": 20,
            "nsl_acc": 0.750808363871524,
            "cicids_acc": 0.7783708333333333,
            "avg_bytes": 1289256.0,
            "time_s": 89.17066359519958
        }
    ]
}